CONTRIBUTORS
LICENSE.txt
MANIFEST.in
README.rst
setup.py
django_image_cropping_amazon_s3.egg-info/PKG-INFO
django_image_cropping_amazon_s3.egg-info/SOURCES.txt
django_image_cropping_amazon_s3.egg-info/dependency_links.txt
django_image_cropping_amazon_s3.egg-info/requires.txt
django_image_cropping_amazon_s3.egg-info/top_level.txt
image_cropping/__init__.py
image_cropping/admin.py
image_cropping/config.py
image_cropping/fields.py
image_cropping/thumbnail_processors.py
image_cropping/utils.py
image_cropping/widgets.py
image_cropping/static/image_cropping/image_cropping.js
image_cropping/static/image_cropping/css/Jcrop.gif
image_cropping/static/image_cropping/css/image_cropping.css
image_cropping/static/image_cropping/css/jquery.Jcrop.css
image_cropping/static/image_cropping/css/jquery.Jcrop.min.css
image_cropping/static/image_cropping/js/jquery.Jcrop.js
image_cropping/static/image_cropping/js/jquery.Jcrop.min.js
image_cropping/static/image_cropping/js/jquery.color.js
image_cropping/templatetags/__init__.py
image_cropping/templatetags/cropping.py