Metadata-Version: 1.1
Name: django-image-cropping-amazon-s3
Version: 0.0.19
Summary: A reusable app for cropping images easily and non-destructively in Django when using Amazon s3 storage for media files
Home-page: http://github.com/nerver/django-image-cropping-amazon-s3
Author: seanslipetz
Author-email: seanslipetz@gmail.com
License: UNKNOWN
Platform: UNKNOWN
Classifier: Development Status :: 5 - Production/Stable
Classifier: Environment :: Web Environment
Classifier: Framework :: Django
Classifier: Intended Audience :: Developers
Classifier: Operating System :: OS Independent
Classifier: Programming Language :: Python
Classifier: Topic :: Software Development :: Libraries :: Python Modules
Classifier: Programming Language :: Python
Classifier: Programming Language :: Python :: 2.7
Classifier: Programming Language :: Python :: 3
Classifier: Programming Language :: Python :: 3.3
